<?xml version="1.0"?>
<aws:UrlInfoResponse xmlns:aws="http://alexa.amazonaws.com/doc/2005-10-05/"><aws:Response xmlns:aws="http://awis.amazonaws.com/doc/2005-07-11"><aws:OperationRequest><aws:RequestId>bc55ee5f-e0d7-20c6-20e8-033f5929d7cc</aws:RequestId></aws:OperationRequest><aws:UrlInfoResult><aws:Alexa>
  
  <aws:ContactInfo>
    <aws:DataUrl type="canonical">webcoders.dk</aws:DataUrl>
    <aws:PhoneNumbers>
      <aws:PhoneNumber>36965136</aws:PhoneNumber>
    </aws:PhoneNumbers>
    <aws:OwnerName>WebCoders</aws:OwnerName>
    <aws:Email>mf@webcoders.dk</aws:Email>
    <aws:PhysicalAddress>
      <aws:Streets>
        <aws:Street>Tørskindvej 10</aws:Street>
      </aws:Streets>
      <aws:City>Bredsten</aws:City>
      <aws:PostalCode>7182</aws:PostalCode>
      <aws:Country>Danmark</aws:Country>
    </aws:PhysicalAddress>
    <aws:CompanyStockTicker/>
  </aws:ContactInfo>
  <aws:ContentData>
    <aws:DataUrl type="canonical">webcoders.dk</aws:DataUrl>
    <aws:SiteData>
      <aws:Title>WebCoders - Komplet Hjemmeside | CMS &amp; Programmering | E-Butik | SEO | IT Outsourcing | Webhotel</aws:Title>
      <aws:Description>Hos WebCoders fokuserer vi på at levere kvalitets hjemmesider, til en priser de alle kan være med til. Vi har siden 2004 arbejdet, samt specialiseret os, indenfor følgende områder: Hjemmeside, E-Butik, CMS &amp; programmering, Søgemaskineoptimering, IT outsourcing og Web-hotel. Har du spørgsmål til et it-projekt eller ønsker du en ny it-partner, så ring til WebCoders på telefon: 36 96 51 36. Vi hjælper altid gerne din virksomhed på vej, til et godt resultat på Internettet.</aws:Description>
    </aws:SiteData>
    <aws:Speed>
      <aws:MedianLoadTime>968</aws:MedianLoadTime>
      <aws:Percentile>72</aws:Percentile>
    </aws:Speed>
    <aws:AdultContent/>
    <aws:Language>
      <aws:Locale>en</aws:Locale>
      <aws:Encoding>us-ascii</aws:Encoding>
    </aws:Language>
    <aws:LinksInCount>138</aws:LinksInCount>
    <aws:Keywords/>
    <aws:OwnedDomains/>
  </aws:ContentData>
  <aws:Related>
    <aws:DataUrl type="canonical">webcoders.dk</aws:DataUrl>
    <aws:RelatedLinks/>
  </aws:Related>
  <aws:TrafficData>
    <aws:DataUrl type="canonical">webcoders.dk</aws:DataUrl>
    <aws:Rank>462652</aws:Rank>
    <aws:RankByCountry>
      <aws:Country Code="DK">
        <aws:Rank>5089</aws:Rank>
        <aws:Contribution>
          <aws:PageViews>87.4%</aws:PageViews>
          <aws:Users>74.9%</aws:Users>
        </aws:Contribution>
      </aws:Country>
      <aws:Country Code="O">
        <aws:Rank/>
        <aws:Contribution>
          <aws:PageViews>12.5%</aws:PageViews>
          <aws:Users>24.8%</aws:Users>
        </aws:Contribution>
      </aws:Country>
    </aws:RankByCountry>
    <aws:RankByCity/>
    <aws:UsageStatistics>
      <aws:UsageStatistic>
        <aws:TimeRange>
          <aws:Months>3</aws:Months>
        </aws:TimeRange>
        <aws:Rank>
          <aws:Value>462652</aws:Value>
          <aws:Delta>+40655</aws:Delta>
        </aws:Rank>
        <aws:Reach>
          <aws:Rank>
            <aws:Value>491462</aws:Value>
            <aws:Delta>+28002</aws:Delta>
          </aws:Rank>
          <aws:PerMillion>
            <aws:Value>2.7</aws:Value>
            <aws:Delta>-7.33%</aws:Delta>
          </aws:PerMillion>
        </aws:Reach>
        <aws:PageViews>
          <aws:PerMillion>
            <aws:Value>0.1</aws:Value>
            <aws:Delta>-19.86%</aws:Delta>
          </aws:PerMillion>
          <aws:Rank>
            <aws:Value>491024</aws:Value>
            <aws:Delta>76070</aws:Delta>
          </aws:Rank>
          <aws:PerUser>
            <aws:Value>3.7</aws:Value>
            <aws:Delta>-13.30%</aws:Delta>
          </aws:PerUser>
        </aws:PageViews>
      </aws:UsageStatistic>
      <aws:UsageStatistic>
        <aws:TimeRange>
          <aws:Months>1</aws:Months>
        </aws:TimeRange>
        <aws:Rank>
          <aws:Value>782554</aws:Value>
          <aws:Delta>+403391</aws:Delta>
        </aws:Rank>
        <aws:Reach>
          <aws:Rank>
            <aws:Value>846807</aws:Value>
            <aws:Delta>+446526</aws:Delta>
          </aws:Rank>
          <aws:PerMillion>
            <aws:Value>1.5</aws:Value>
            <aws:Delta>-58.99%</aws:Delta>
          </aws:PerMillion>
        </aws:Reach>
        <aws:PageViews>
          <aws:PerMillion>
            <aws:Value>0.05</aws:Value>
            <aws:Delta>-59.43%</aws:Delta>
          </aws:PerMillion>
          <aws:Rank>
            <aws:Value>795057</aws:Value>
            <aws:Delta>377067</aws:Delta>
          </aws:Rank>
          <aws:PerUser>
            <aws:Value>3.5</aws:Value>
            <aws:Delta>-1.13%</aws:Delta>
          </aws:PerUser>
        </aws:PageViews>
      </aws:UsageStatistic>
      <aws:UsageStatistic>
        <aws:TimeRange>
          <aws:Days>7</aws:Days>
        </aws:TimeRange>
        <aws:Rank>
          <aws:Value>545342</aws:Value>
          <aws:Delta>-51758</aws:Delta>
        </aws:Rank>
        <aws:Reach>
          <aws:Rank>
            <aws:Value>466640</aws:Value>
            <aws:Delta>-84698</aws:Delta>
          </aws:Rank>
          <aws:PerMillion>
            <aws:Value>2.9</aws:Value>
            <aws:Delta>+20%</aws:Delta>
          </aws:PerMillion>
        </aws:Reach>
        <aws:PageViews>
          <aws:PerMillion>
            <aws:Value>0.05</aws:Value>
            <aws:Delta>-3.72%</aws:Delta>
          </aws:PerMillion>
          <aws:Rank>
            <aws:Value>870512</aws:Value>
            <aws:Delta>16181</aws:Delta>
          </aws:Rank>
          <aws:PerUser>
            <aws:Value>1.5</aws:Value>
            <aws:Delta>-18.95%</aws:Delta>
          </aws:PerUser>
        </aws:PageViews>
      </aws:UsageStatistic>
    </aws:UsageStatistics>
    <aws:ContributingSubdomains>
      <aws:ContributingSubdomain>
        <aws:DataUrl>webcoders.dk</aws:DataUrl>
        <aws:TimeRange>
          <aws:Months>1</aws:Months>
        </aws:TimeRange>
        <aws:Reach>
          <aws:Percentage>69.17%</aws:Percentage>
        </aws:Reach>
        <aws:PageViews>
          <aws:Percentage>80.34%</aws:Percentage>
          <aws:PerUser>4</aws:PerUser>
        </aws:PageViews>
      </aws:ContributingSubdomain>
      <aws:ContributingSubdomain>
        <aws:DataUrl>OTHER</aws:DataUrl>
        <aws:TimeRange>
          <aws:Months>1</aws:Months>
        </aws:TimeRange>
        <aws:Reach>
          <aws:Percentage>0</aws:Percentage>
        </aws:Reach>
        <aws:PageViews>
          <aws:Percentage>19.73%</aws:Percentage>
          <aws:PerUser>0</aws:PerUser>
        </aws:PageViews>
      </aws:ContributingSubdomain>
    </aws:ContributingSubdomains>
  </aws:TrafficData>
</aws:Alexa></aws:UrlInfoResult><aws:ResponseStatus xmlns:aws="http://alexa.amazonaws.com/doc/2005-10-05/"><aws:StatusCode>Success</aws:StatusCode></aws:ResponseStatus></aws:Response></aws:UrlInfoResponse>